tgit/__init__.py
tgit/add.py
tgit/changelog.py
tgit/cli.py
tgit/commit.py
tgit/constants.py
tgit/interactive_settings.py
tgit/settings.py
tgit/shared.py
tgit/types.py
tgit/version.py
tgit/prompts/commit.txt
tgit/utils/__init__.py
tgit-0.27.0.dist-info/METADATA
tgit-0.27.0.dist-info/WHEEL
tgit-0.27.0.dist-info/entry_points.txt
tgit-0.27.0.dist-info/RECORD
